clean_df_lib/__init__.py
clean_df_lib/clean_df_lib.py
clean_df_lib-0.1.0.dist-info/LICENSE
clean_df_lib-0.1.0.dist-info/METADATA
clean_df_lib-0.1.0.dist-info/WHEEL
clean_df_lib-0.1.0.dist-info/top_level.txt
clean_df_lib-0.1.0.dist-info/RECORD
